fathom_python/__init__.py
fathom_python/_hooks/__init__.py
fathom_python/_hooks/registration.py
fathom_python/_hooks/sdkhooks.py
fathom_python/_hooks/types.py
fathom_python/_version.py
fathom_python/basesdk.py
fathom_python/errors/__init__.py
fathom_python/errors/apierror.py
fathom_python/errors/fathomerror.py
fathom_python/errors/no_response_error.py
fathom_python/errors/responsevalidationerror.py
fathom_python/httpclient.py
fathom_python/models/__init__.py
fathom_python/models/actionitem.py
fathom_python/models/assignee.py
fathom_python/models/callbackresponse.py
fathom_python/models/createwebhookop.py
fathom_python/models/crmcompanymatch.py
fathom_python/models/crmcontactmatch.py
fathom_python/models/crmdealmatch.py
fathom_python/models/crmmatches.py
fathom_python/models/deletewebhookop.py
fathom_python/models/fathomuser.py
fathom_python/models/getrecordingsummaryop.py
fathom_python/models/getrecordingtranscriptop.py
fathom_python/models/invitee.py
fathom_python/models/listmeetingsop.py
fathom_python/models/listteammembersop.py
fathom_python/models/listteamsop.py
fathom_python/models/meeting.py
fathom_python/models/meetinglistresponse.py
fathom_python/models/meetingsummary.py
fathom_python/models/security.py
fathom_python/models/team.py
fathom_python/models/teamlistresponse.py
fathom_python/models/teammember.py
fathom_python/models/teammemberlistresponse.py
fathom_python/models/transcriptitem.py
fathom_python/models/transcriptitemspeaker.py
fathom_python/models/webhook.py
fathom_python/py.typed
fathom_python/sdk.py
fathom_python/sdkconfiguration.py
fathom_python/types/__init__.py
fathom_python/types/basemodel.py
fathom_python/utils/__init__.py
fathom_python/utils/annotations.py
fathom_python/utils/datetimes.py
fathom_python/utils/enums.py
fathom_python/utils/eventstreaming.py
fathom_python/utils/forms.py
fathom_python/utils/headers.py
fathom_python/utils/logger.py
fathom_python/utils/metadata.py
fathom_python/utils/queryparams.py
fathom_python-0.0.36.dist-info/METADATA
fathom_python-0.0.36.dist-info/WHEEL
fathom_python-0.0.36.dist-info/RECORD
