Metadata-Version: 2.3
Name: fathom-python
Version: 0.0.36
Summary: Fathom's official Python SDK.
Author: Speakeasy
Requires-Python: >=3.9.2
Classifier: Programming Language :: Python :: 3
Classifier: Programming Language :: Python :: 3.10
Classifier: Programming Language :: Python :: 3.11
Classifier: Programming Language :: Python :: 3.12
Classifier: Programming Language :: Python :: 3.13
Requires-Dist: httpcore (>=1.0.9)
Requires-Dist: httpx (>=0.28.1)
Requires-Dist: jsonpath-python (>=1.0.6)
Requires-Dist: pydantic (>=2.11.2)
Requires-Dist: requests (>=2.32.4,<3.0.0)
Requires-Dist: svix (>=1.65.0,<2.0.0)
Requires-Dist: types-requests (>=2.32.4,<3.0.0)
